sunrise_repos/__init__.py
sunrise_repos/cli.py
sunrise_repos/unarchive.py
sunrise_repos-1.0.3.dist-info/LICENSE.txt
sunrise_repos-1.0.3.dist-info/METADATA
sunrise_repos-1.0.3.dist-info/WHEEL
sunrise_repos-1.0.3.dist-info/entry_points.txt
sunrise_repos-1.0.3.dist-info/top_level.txt
sunrise_repos-1.0.3.dist-info/RECORD
