Metadata-Version: 2.1
Name: sunrise-repos
Version: 1.0.3
Summary: Unarchive batches of GitHub repositories
Home-page: https://github.com/th-yoon/sunrise-repos
Author: Taehyun Yoon
Author-email: taehyun.yoon.fm@gmail.com
Classifier: Programming Language :: Python :: 3
Classifier: License :: OSI Approved :: MIT License
Classifier: Operating System :: OS Independent
Requires-Python: >=3.6
License-File: LICENSE.txt
Requires-Dist: Click (>=7.0)
Requires-Dist: requests (>=2.22.0)
